[{"name":"api","commit":{"id":"f7dd067490fe57505f7226c3b54d3127d2f7fd46","parents":[{"id":"949b1df930bedace1dbd755aaa4a82e8c451a616"}],"tree":"f8c4b21c036339f92fcc5482aa28a41250553b27","message":"API: expose issues project id","author":{"name":"Nihad Abbasov","email":"narkoz.2008@gmail.com"},"committer":{"name":"Nihad Abbasov","email":"narkoz.2008@gmail.com"},"authored_date":"2012-07-25T04:22:21-07:00","committed_date":"2012-07-25T04:22:21-07:00"}},{"name":"dashboard-feed","commit":{"id":"f8f6ff065eccc6ede4d35ed87a09bb962b84ca25","parents":[{"id":"2cf8010792c3075824ee27d0f037aeb178cbbf7e"}],"tree":"e17f2157143d550891d4669c10b7446e4739bc6d","message":"add projects atom feed","author":{"name":"Nihad Abbasov","email":"narkoz.2008@gmail.com"},"committer":{"name":"Nihad Abbasov","email":"narkoz.2008@gmail.com"},"authored_date":"2012-05-31T23:42:02-07:00","committed_date":"2012-05-31T23:42:02-07:00"}},{"name":"master","commit":{"id":"2cf8010792c3075824ee27d0f037aeb178cbbf7e","parents":[{"id":"af226ae9c9af406c8a0e0bbdf364563495c2f432"},{"id":"e851cb07762aa464aae10e8b4b28de87c1a6f925"}],"tree":"6c6845838039f01723d91f395a1d2fa1dcc82522","message":"Merge pull request #868 from SaitoWu/bugfix/encoding\n\nBugfix/encoding","author":{"name":"Dmitriy Zaporozhets","email":"dmitriy.zaporozhets@gmail.com"},"committer":{"name":"Dmitriy Zaporozhets","email":"dmitriy.zaporozhets@gmail.com"},"authored_date":"2012-05-30T00:24:43-07:00","committed_date":"2012-05-30T00:24:43-07:00"}},{"name":"preview_notes","commit":{"id":"3749e0d99ac6bfbc65889b1b7a5310e14e7fe89a","parents":[{"id":"2483181f2c3d4ea7d2c68147b19bc07fc3937b0c"}],"tree":"f8c56161b0d6561568f088df9961362eb1ece88b","message":"pass project_id to notes preview path","author":{"name":"Nihad Abbasov","email":"narkoz.2008@gmail.com"},"committer":{"name":"Nihad Abbasov","email":"narkoz.2008@gmail.com"},"authored_date":"2012-08-09T23:46:27-07:00","committed_date":"2012-08-09T23:46:27-07:00"}},{"name":"refactoring","commit":{"id":"7c7761099cae83f59fe5780340e100be890847b2","parents":[{"id":"058d80b3363dd4fc4417ca4f60f76119188a2470"}],"tree":"d7d4a94c700dc0e84ee943019213d2358a49c413","message":"fix deprecation warnings","author":{"name":"Nihad Abbasov","email":"narkoz.2008@gmail.com"},"committer":{"name":"Nihad Abbasov","email":"narkoz.2008@gmail.com"},"authored_date":"2012-05-29T07:16:28-07:00","committed_date":"2012-05-29T07:16:28-07:00"}}]
