[{"id":1,"iid":1,"project_id":1,"title":"lorem ipsum","description":"","state":"opened","created_at":"2017-03-24T12:23:53.918Z","updated_at":"2017-03-24T12:23:53.918Z","target_branch":"master","source_branch":"def","upvotes":0,"downvotes":0,"author":{"name":"John Doe","username":"jdoe","id":1,"state":"active","avatar_url":"","web_url":"https://gitlab.com/jdoen"},"assignee":null,"source_project_id":1,"target_project_id":1,"labels":[],"work_in_progress":false,"milestone":{"id":1,"iid":1,"project_id":1,"title":"Test","description":"","state":"active","created_at":"2017-03-24T12:23:00.560Z","updated_at":"2017-03-24T12:23:00.560Z","due_date":null,"start_date":null},"merge_when_pipeline_succeeds":false,"merge_status":"can_be_merged","sha":"aec123d1775790b2347fdd684b5ba613fdeb994b","merge_commit_sha":null,"user_notes_count":0,"approvals_before_merge":null,"should_remove_source_branch":null,"force_remove_source_branch":false,"squash":false,"web_url":"https://gitlab.com/jdoe/milestone_merge_requests_test/merge_requests/2"},{"id":2,"iid":2,"project_id":1,"title":"ipsum lorem","description":"","state":"opened","created_at":"2017-03-24T12:23:24.662Z","updated_at":"2017-03-24T12:23:33.522Z","target_branch":"master","source_branch":"test1","upvotes":0,"downvotes":0,"author":{"name":"Joren","username":"jdoe","id":1,"state":"active","":"","web_url":"https://gitlab.com/jdoe"},"assignee":null,"source_project_id":1,"target_project_id":1,"labels":[],"work_in_progress":false,"milestone":{"id":1,"iid":1,"project_id":1,"title":"Test","description":"","state":"active","created_at":"2017-03-24T12:23:00.560Z","updated_at":"2017-03-24T12:23:00.560Z","due_date":null,"start_date":null},"merge_when_pipeline_succeeds":false,"merge_status":"can_be_merged","sha":"3ee44c9b40deddae596f838b97523c6f010fd80d","merge_commit_sha":null,"user_notes_count":0,"approvals_before_merge":null,"should_remove_source_branch":null,"force_remove_source_branch":true,"squash":false,"web_url":"https://gitlab.com/jdoe/milestone_merge_requests_test/merge_requests/1"}]
